{
    "version": "0.1.20250724",
    "status_code": 20000,
    "status_message": "Ok.",
    "time": "47.0865 sec.",
    "cost": 0.009,
    "tasks_count": 1,
    "tasks_error": 0,
    "tasks": [
        {
            "id": "07242233-1084-0173-0000-e63311e3539b",
            "status_code": 20000,
            "status_message": "Ok.",
            "time": "47.0494 sec.",
            "cost": 0.009,
            "result_count": 1,
            "path": [
                "v3",
                "keywords_data",
                "google_trends",
                "explore",
                "live"
            ],
            "data": {
                "api": "keywords_data",
                "function": "explore",
                "se": "google_trends",
                "keywords": [
                    "내비실거리제"
                ],
                "location_code": 2410,
                "language_code": "ko",
                "type": "web",
                "date_from": "2009-01-01",
                "date_to": "2025-06-30"
            },
            "result": [
                {
                    "keywords": [
                        "내비실거리제"
                    ],
                    "type": "trends",
                    "location_code": 2410,
                    "language_code": "ko",
                    "check_url": "https://trends.google.com/trends/explore?hl=ko&geo=KR&date=2009-01-01%202025-06-30&q=%EB%82%B4%EB%B9%84%EC%8B%A4%EA%B1%B0%EB%A6%AC%EC%A0%9C",
                    "datetime": "2025-07-24 19:34:22 +00:00",
                    "items_count": 1,
                    "items": [
                        {
                            "position": 1,
                            "type": "google_trends_graph",
                            "title": null,
                            "keywords": [
                                "내비실거리제"
                            ],
                            "data": null,
                            "averages": []
                        }
                    ]
                }
            ]
        }
    ]
}